fastdcm/__init__.py
fastdcm/__main__.py
fastdcm-0.1.0.dist-info/entry_points.txt
fastdcm-0.1.0.dist-info/METADATA
fastdcm-0.1.0.dist-info/WHEEL
fastdcm-0.1.0.dist-info/RECORD
